setup.py
swk_foreman/__init__.py
swk_foreman/swk_foreman.py
swk_foreman/version.py
swk_foreman.egg-info/PKG-INFO
swk_foreman.egg-info/SOURCES.txt
swk_foreman.egg-info/dependency_links.txt
swk_foreman.egg-info/entry_points.txt
swk_foreman.egg-info/requires.txt
swk_foreman.egg-info/top_level.txt